wxcadm/__init__.py
wxcadm/announcements.py
wxcadm/applications.py
wxcadm/auto_attendant.py
wxcadm/bifrost.py
wxcadm/call_queue.py
wxcadm/call_routing.py
wxcadm/calls.py
wxcadm/cdr.py
wxcadm/common.py
wxcadm/cpapi.py
wxcadm/dect.py
wxcadm/device.py
wxcadm/events.py
wxcadm/exceptions.py
wxcadm/hunt_group.py
wxcadm/jobs.py
wxcadm/location.py
wxcadm/location_features.py
wxcadm/meraki.py
wxcadm/models.py
wxcadm/monitoring.py
wxcadm/number.py
wxcadm/org.py
wxcadm/person.py
wxcadm/pickup_group.py
wxcadm/pstn.py
wxcadm/realtime.py
wxcadm/recording.py
wxcadm/redsky.py
wxcadm/reports.py
wxcadm/virtual_line.py
wxcadm/webex.py
wxcadm/webhooks.py
wxcadm/wholesale.py
wxcadm/workspace.py
wxcadm/xsi.py
wxcadm/xsi_response.py
wxcadm-4.6.1.dist-info/licenses/LICENSE
wxcadm-4.6.1.dist-info/METADATA
wxcadm-4.6.1.dist-info/WHEEL
wxcadm-4.6.1.dist-info/top_level.txt
wxcadm-4.6.1.dist-info/RECORD
