Metadata-Version: 2.4
Name: wxcadm
Version: 4.6.1
Summary: A Python 3 library for Webex Calling administrators
Author-email: Trey Hilyard <kctrey@gmail.com>
License-Expression: GPL-3.0-or-later
Project-URL: Homepage, https://github.com/kctrey/wxcadm
Project-URL: Issues, https://github.com/kctrey/wxcadm/issues
Project-URL: Documentation, https://wxcadm.readthedocs.io
Project-URL: Changelog, https://wxcadm.readthedocs.io/en/latest/whatsnew.html
Classifier: Intended Audience :: Developers
Classifier: Programming Language :: Python :: 3
Classifier: Operating System :: OS Independent
Requires-Python: >=3.8
License-File: LICENSE
Requires-Dist: requests>=2.31.0
Requires-Dist: requests-toolbelt>=1.0.0
Requires-Dist: srvlookup>=2.0.0
Requires-Dist: xmltodict>=0.12.0
Requires-Dist: pyhumps==3.8.0
Requires-Dist: dataclasses-json>=0.6.4
Provides-Extra: meraki
Requires-Dist: meraki>=1.30.0; extra == "meraki"
Dynamic: license-file
